pydantic_ghostfolio/__init__.py
pydantic_ghostfolio/models.py
pydantic_ghostfolio/py.typed
pydantic_ghostfolio-0.1.1.dist-info/METADATA
pydantic_ghostfolio-0.1.1.dist-info/WHEEL
pydantic_ghostfolio-0.1.1.dist-info/entry_points.txt
pydantic_ghostfolio-0.1.1.dist-info/licenses/LICENSE
pydantic_ghostfolio-0.1.1.dist-info/RECORD
